src/kitcat/__init__.py
src/kitcat/backend.py
src/kitcat/utils.py
kitcat-1.2.1.dist-info/METADATA
kitcat-1.2.1.dist-info/WHEEL
kitcat-1.2.1.dist-info/entry_points.txt
kitcat-1.2.1.dist-info/licenses/LICENSE
kitcat-1.2.1.dist-info/RECORD
