Metadata-Version: 2.4
Name: kitcat
Version: 1.2.1
Summary: Matplotlib backend for direct plotting in the terminal using Kitty graphics protocol.
Project-URL: Repository, https://github.com/mil-ad/kitcat.git
Project-URL: Issues, https://github.com/mil-ad/kitcat/issues
Author-email: Milad Alizadeh <git@mil.ad>
License: MIT License
License-File: LICENSE
Keywords: kitty,matplotlib
Requires-Python: >=3.9
Requires-Dist: matplotlib>=3.9
